ebikeconnect/__init__.py
ebikeconnect/_version.py
ebikeconnect/client.py
ebikeconnect/models.py
ebikeconnect/py.typed
ebike_connect-0.0.2.dist-info/METADATA
ebike_connect-0.0.2.dist-info/WHEEL
ebike_connect-0.0.2.dist-info/top_level.txt
ebike_connect-0.0.2.dist-info/RECORD
