Metadata-Version: 2.4
Name: ebike-connect
Version: 0.0.2
Summary: Python client for Bosch eBike Connect.
Author-email: Rogier van der Geer <rogier@vander-geer.nl>
License: MIT
Project-URL: Repository, https://github.com/rogiervandergeer/ebike-connect
Keywords: api,bosch,ebike
Classifier: Intended Audience :: Developers
Classifier: License :: OSI Approved :: MIT License
Classifier: Operating System :: OS Independent
Classifier: Programming Language :: Python :: 3
Classifier: Typing :: Typed
Requires-Python: >=3.11
Requires-Dist: pydantic>=2.10.0
Requires-Dist: requests>=2.31.0
Provides-Extra: dev
Requires-Dist: pre-commit>=3.3.3; extra == "dev"
Requires-Dist: ruff>=0.8.1; extra == "dev"
Requires-Dist: pytest>=8.1.0; extra == "dev"
Requires-Dist: pytest-mock>=3.13.0; extra == "dev"
